judini/__init__.py
judini/agent.py
judini_dev-0.0.11.dist-info/LICENSE
judini_dev-0.0.11.dist-info/METADATA
judini_dev-0.0.11.dist-info/WHEEL
judini_dev-0.0.11.dist-info/top_level.txt
judini_dev-0.0.11.dist-info/RECORD
