Metadata-Version: 2.1
Name: judini-dev
Version: 0.0.11
Summary: Judini python package
Home-page: https://github.com/JudiniLabs/judini-python.git
Author: Judini
Author-email: hablemos@judini.ai
Classifier: Programming Language :: Python :: 3
Classifier: License :: OSI Approved :: MIT License
Classifier: Operating System :: OS Independent
Requires-Python: >=3.6
License-File: LICENSE
